cedar/__init__.py
cedar/_version.py
cedar/defaults.py
cedar/exceptions.py
cedar/ordering.py
cedar/preard.py
cedar/tracker.py
cedar/utils.py
cedar/validation.py
cedar/cli/__init__.py
cedar/cli/auth.py
cedar/cli/config.py
cedar/cli/console.py
cedar/cli/convert.py
cedar/cli/gee.py
cedar/cli/main.py
cedar/cli/options.py
cedar/cli/status.py
cedar/cli/storage.py
cedar/cli/submit.py
cedar/config/__init__.py
cedar/config/build.py
cedar/config/config.yaml.tmpl
cedar/config/core.py
cedar/config/schema.json
cedar/metadata/__init__.py
cedar/metadata/core.py
cedar/metadata/schema_definitions.json
cedar/metadata/schema_image.json
cedar/metadata/schema_tracking.json
cedar/metadata/tracking.py
cedar/metadata/tests/data/example_metadata_image.json
cedar/metadata/tests/data/example_metadata_tracking.json
cedar/sensors/__init__.py
cedar/sensors/common.py
cedar/sensors/landsat.py
cedar/stores/__init__.py
cedar/stores/gcs.py
cedar/stores/gdrive.py
cedar/tests/__init__.py
cedar/tests/conftest.py
cedar/tests/test_cedar.py
cedar/tests/test_preard.py
cedar/tests/test_tracker.py
cedar/tests/test_utils.py
cedar_datacube-0.0.4.dist-info/LICENSE
cedar_datacube-0.0.4.dist-info/METADATA
cedar_datacube-0.0.4.dist-info/WHEEL
cedar_datacube-0.0.4.dist-info/entry_points.txt
cedar_datacube-0.0.4.dist-info/top_level.txt
cedar_datacube-0.0.4.dist-info/RECORD
