Metadata-Version: 2.1
Name: cedar-datacube
Version: 0.0.4
Summary: Creator for Analysis Ready Data (ARD)
Home-page: https://github.com/ceholden/cedar-datacube
Author: Chris Holden
Author-email: ceholden@gmail.com
License: ('BSD license',)
Platform: UNKNOWN
Classifier: Development Status :: 3 - Alpha
Classifier: Intended Audience :: Developers
Classifier: License :: OSI Approved :: BSD License
Classifier: Natural Language :: English
Classifier: Programming Language :: Python :: 3
Classifier: Programming Language :: Python :: 3 :: Only
Classifier: Programming Language :: Python :: 3.6
Classifier: Programming Language :: Python :: 3.7
Classifier: Topic :: Software Development :: Libraries
Classifier: Topic :: Scientific/Engineering :: GIS
Requires-Python: >=3.6
Requires-Dist: earthengine-api
Requires-Dist: affine
Requires-Dist: numpy
Requires-Dist: pandas
Requires-Dist: rasterio
Requires-Dist: shapely
Requires-Dist: xarray
Requires-Dist: jsonschema
Requires-Dist: pyyaml
Requires-Dist: click (>=6.0)
Requires-Dist: click-plugins
Requires-Dist: cligj (>=0.5)
Provides-Extra: all
Requires-Dist: affine ; extra == 'all'
Requires-Dist: click-plugins ; extra == 'all'
Requires-Dist: click (>=6.0) ; extra == 'all'
Requires-Dist: cligj (>=0.5) ; extra == 'all'
Requires-Dist: coverage ; extra == 'all'
Requires-Dist: earthengine-api ; extra == 'all'
Requires-Dist: google-api-python-client ; extra == 'all'
Requires-Dist: google-auth-httplib2 ; extra == 'all'
Requires-Dist: google-auth-oauthlib ; extra == 'all'
Requires-Dist: google-cloud-storage ; extra == 'all'
Requires-Dist: jsonschema ; extra == 'all'
Requires-Dist: numpy ; extra == 'all'
Requires-Dist: numpydoc ; extra == 'all'
Requires-Dist: pandas ; extra == 'all'
Requires-Dist: pytest ; extra == 'all'
Requires-Dist: pytest-cov ; extra == 'all'
Requires-Dist: pytest-lazy-fixture ; extra == 'all'
Requires-Dist: pyyaml ; extra == 'all'
Requires-Dist: rasterio ; extra == 'all'
Requires-Dist: shapely ; extra == 'all'
Requires-Dist: sphinx ; extra == 'all'
Requires-Dist: sphinx-rtd-theme ; extra == 'all'
Requires-Dist: sphinxcontrib-bibtex ; extra == 'all'
Requires-Dist: sphinxcontrib-programoutput ; extra == 'all'
Requires-Dist: stems ; extra == 'all'
Requires-Dist: xarray ; extra == 'all'
Provides-Extra: core
Requires-Dist: earthengine-api ; extra == 'core'
Requires-Dist: affine ; extra == 'core'
Requires-Dist: numpy ; extra == 'core'
Requires-Dist: pandas ; extra == 'core'
Requires-Dist: rasterio ; extra == 'core'
Requires-Dist: shapely ; extra == 'core'
Requires-Dist: xarray ; extra == 'core'
Requires-Dist: jsonschema ; extra == 'core'
Requires-Dist: pyyaml ; extra == 'core'
Requires-Dist: click (>=6.0) ; extra == 'core'
Requires-Dist: click-plugins ; extra == 'core'
Requires-Dist: cligj (>=0.5) ; extra == 'core'
Provides-Extra: gcs
Requires-Dist: google-cloud-storage ; extra == 'gcs'
Provides-Extra: gdrive
Requires-Dist: google-api-python-client ; extra == 'gdrive'
Requires-Dist: google-auth-httplib2 ; extra == 'gdrive'
Requires-Dist: google-auth-oauthlib ; extra == 'gdrive'
Provides-Extra: tests
Requires-Dist: stems ; extra == 'tests'
Requires-Dist: pytest ; extra == 'tests'
Requires-Dist: pytest-cov ; extra == 'tests'
Requires-Dist: pytest-lazy-fixture ; extra == 'tests'
Requires-Dist: coverage ; extra == 'tests'
Requires-Dist: sphinx ; extra == 'tests'
Requires-Dist: sphinx-rtd-theme ; extra == 'tests'
Requires-Dist: sphinxcontrib-programoutput ; extra == 'tests'
Requires-Dist: sphinxcontrib-bibtex ; extra == 'tests'
Requires-Dist: numpydoc ; extra == 'tests'
